qaga/__init__.py
qaga/genetic_algorithm.py
qaga/mutation/__init__.py
qaga/mutation/addition_mutation.py
qaga/mutation/identity_mutation.py
qaga/mutation/mutation.py
qaga/mutation/reverse_annealing_mutation.py
qaga/mutation/sampler_mutation.py
qaga/problem.py
qaga/recombination/__init__.py
qaga/recombination/addition_recombination.py
qaga/recombination/identity_recombination.py
qaga/recombination/pair_recombination.py
qaga/recombination/random_bits_recombination.py
qaga/recombination/random_cluster_recombination.py
qaga/recombination/random_sections_recombination.py
qaga/recombination/recombination.py
qaga/selection/__init__.py
qaga/selection/identity_selection.py
qaga/selection/pareto_selection.py
qaga/selection/refilling_selection.py
qaga/selection/selection.py
qaga/selection/truncation_selection.py
qaga/simple.py
qaga/startup/__init__.py
qaga/startup/random_startup.py
qaga/startup/sampling_startup.py
qaga/startup/startup.py
qaga/startup/warm_startup.py
qaga/termination/__init__.py
qaga/termination/and_termination.py
qaga/termination/generation_termination.py
qaga/termination/lowest_energy_evaluation.py
qaga/termination/or_termination.py
qaga/termination/population_size_termination.py
qaga/termination/termination.py
qaga/testing/creation.py
qaga/testing/mutation.py
qaga/testing/population.py
qaga-0.0.4.dist-info/LICENSE
qaga-0.0.4.dist-info/WHEEL
qaga-0.0.4.dist-info/METADATA
qaga-0.0.4.dist-info/RECORD
