Metadata-Version: 2.1
Name: qaga
Version: 0.0.4
Summary: 
Author: dokunogakusha
Author-email: 94387179+dokunogakusha@users.noreply.github.com
Requires-Python: >=3.7,<4.0
Classifier: Programming Language :: Python :: 3
Classifier: Programming Language :: Python :: 3.10
Classifier: Programming Language :: Python :: 3.7
Classifier: Programming Language :: Python :: 3.8
Classifier: Programming Language :: Python :: 3.9
Requires-Dist: dimod (>=0.10.15,<0.11.0)
Requires-Dist: dwave-neal (>=0.5.9,<0.6.0)
Requires-Dist: dwave-system (>=1.11.0,<2.0.0)
Requires-Dist: toolz (>=0.11.2,<0.12.0)
